CHANGELOG.txt
LICENCE.txt
MANIFEST.in
README.txt
setup.py
Kashier/__init__.py
Kashier.egg-info/PKG-INFO
Kashier.egg-info/SOURCES.txt
Kashier.egg-info/dependency_links.txt
Kashier.egg-info/requires.txt
Kashier.egg-info/top_level.txt